{
  "edinet_code": "E00161",
  "name": "明星工業株式会社",
  "sec_code": "19760",
  "industry": "建設業",
  "peer_group": "建設業",
  "is_holding": false,
  "latest": {
    "source": {
      "doc_type": "有価証券報告書",
      "doc_id": "S100YFOI",
      "period_end": "2026-03-31",
      "submit_datetime": "2026-06-22 12:55",
      "description": "有価証券報告書－第84期(2025/04/01－2026/03/31)"
    },
    "employees": {
      "consolidated": 768,
      "reporting_company": 362,
      "reporting_company_source": "XBRL標準タグと一致",
      "reporting_company_xbrl_standard_tag": 362,
      "consolidated_history": {
        "当期末": 768,
        "1年前": 756,
        "2年前": 691,
        "3年前": 671,
        "4年前": 651
      }
    },
    "reporting_company": {
      "average_age_years": 39.7,
      "average_tenure_years": 13.8,
      "average_annual_salary_yen": 7260593
    },
    "diversity": {
      "scope": "提出会社",
      "female_manager_ratio": 0.027,
      "female_to_male_wage_ratio_all": 0.791,
      "female_to_male_wage_ratio_regular": 0.791,
      "female_to_male_wage_ratio_nonregular": null,
      "male_childcare_leave_ratio": 0.166,
      "male_childcare_leave_method": "原則方式"
    },
    "subsidiaries": [],
    "notes": [],
    "is_holding": false,
    "basis_change_note": "",
    "reorganization_note": ""
  },
  "years": [
    {
      "source": {
        "doc_type": "有価証券報告書",
        "doc_id": "S100OECF",
        "period_end": "2022-03-31",
        "submit_datetime": "2022-06-24 10:46",
        "description": "有価証券報告書－第80期(令和3年4月1日－令和4年3月31日)"
      },
      "employees": {
        "consolidated": 651,
        "reporting_company": 312,
        "reporting_company_source": "XBRL標準タグと一致",
        "reporting_company_xbrl_standard_tag": 312,
        "consolidated_history": {
          "当期末": 651,
          "1年前": 663,
          "2年前": 658,
          "3年前": 641,
          "4年前": 632
        }
      },
      "reporting_company": {
        "average_age_years": 40.4,
        "average_tenure_years": 14.4,
        "average_annual_salary_yen": 6126630
      },
      "diversity": {
        "scope": null,
        "female_manager_ratio": null,
        "female_to_male_wage_ratio_all": null,
        "female_to_male_wage_ratio_regular": null,
        "female_to_male_wage_ratio_nonregular": null,
        "male_childcare_leave_ratio": null,
        "male_childcare_leave_method": null
      },
      "subsidiaries": [],
      "notes": [
        "多様性指標は有報に記載なし（非公表）。"
      ],
      "is_holding": false,
      "basis_change_note": "",
      "reorganization_note": ""
    },
    {
      "source": {
        "doc_type": "有価証券報告書",
        "doc_id": "S100R6FU",
        "period_end": "2023-03-31",
        "submit_datetime": "2023-06-28 13:03",
        "description": "有価証券報告書－第81期(2022/04/01－2023/03/31)"
      },
      "employees": {
        "consolidated": 671,
        "reporting_company": 335,
        "reporting_company_source": "XBRL標準タグと一致",
        "reporting_company_xbrl_standard_tag": 335,
        "consolidated_history": {
          "当期末": 671,
          "1年前": 651,
          "2年前": 663,
          "3年前": 658,
          "4年前": 641
        }
      },
      "reporting_company": {
        "average_age_years": 39.6,
        "average_tenure_years": 13.5,
        "average_annual_salary_yen": 5850902
      },
      "diversity": {
        "scope": null,
        "female_manager_ratio": null,
        "female_to_male_wage_ratio_all": null,
        "female_to_male_wage_ratio_regular": null,
        "female_to_male_wage_ratio_nonregular": null,
        "male_childcare_leave_ratio": null,
        "male_childcare_leave_method": null
      },
      "subsidiaries": [],
      "notes": [
        "多様性指標は有報に記載なし（非公表）。"
      ],
      "is_holding": false,
      "basis_change_note": "",
      "reorganization_note": ""
    },
    {
      "source": {
        "doc_type": "有価証券報告書",
        "doc_id": "S100TOS3",
        "period_end": "2024-03-31",
        "submit_datetime": "2024-06-21 12:53",
        "description": "有価証券報告書－第82期(2023/04/01－2024/03/31)"
      },
      "employees": {
        "consolidated": 691,
        "reporting_company": 358,
        "reporting_company_source": "XBRL標準タグと一致",
        "reporting_company_xbrl_standard_tag": 358,
        "consolidated_history": {
          "当期末": 691,
          "1年前": 671,
          "2年前": 651,
          "3年前": 663,
          "4年前": 658
        }
      },
      "reporting_company": {
        "average_age_years": 39.9,
        "average_tenure_years": 13.1,
        "average_annual_salary_yen": 5972385
      },
      "diversity": {
        "scope": "提出会社",
        "female_manager_ratio": 0.032,
        "female_to_male_wage_ratio_all": 0.703,
        "female_to_male_wage_ratio_regular": 0.703,
        "female_to_male_wage_ratio_nonregular": null,
        "male_childcare_leave_ratio": 0.05,
        "male_childcare_leave_method": "原則方式"
      },
      "subsidiaries": [],
      "notes": [],
      "is_holding": false,
      "basis_change_note": "",
      "reorganization_note": ""
    },
    {
      "source": {
        "doc_type": "有価証券報告書",
        "doc_id": "S100W3LA",
        "period_end": "2025-03-31",
        "submit_datetime": "2025-06-25 12:46",
        "description": "有価証券報告書－第83期(2024/04/01－2025/03/31)"
      },
      "employees": {
        "consolidated": 756,
        "reporting_company": 383,
        "reporting_company_source": "XBRL標準タグと一致",
        "reporting_company_xbrl_standard_tag": 383,
        "consolidated_history": {
          "当期末": 756,
          "1年前": 691,
          "2年前": 671,
          "3年前": 651,
          "4年前": 663
        }
      },
      "reporting_company": {
        "average_age_years": 39.3,
        "average_tenure_years": 12.6,
        "average_annual_salary_yen": 6146247
      },
      "diversity": {
        "scope": "提出会社",
        "female_manager_ratio": 0.033,
        "female_to_male_wage_ratio_all": 0.764,
        "female_to_male_wage_ratio_regular": 0.764,
        "female_to_male_wage_ratio_nonregular": null,
        "male_childcare_leave_ratio": 0.333,
        "male_childcare_leave_method": "原則方式"
      },
      "subsidiaries": [],
      "notes": [],
      "is_holding": false,
      "basis_change_note": "",
      "reorganization_note": ""
    },
    {
      "source": {
        "doc_type": "有価証券報告書",
        "doc_id": "S100YFOI",
        "period_end": "2026-03-31",
        "submit_datetime": "2026-06-22 12:55",
        "description": "有価証券報告書－第84期(2025/04/01－2026/03/31)"
      },
      "employees": {
        "consolidated": 768,
        "reporting_company": 362,
        "reporting_company_source": "XBRL標準タグと一致",
        "reporting_company_xbrl_standard_tag": 362,
        "consolidated_history": {
          "当期末": 768,
          "1年前": 756,
          "2年前": 691,
          "3年前": 671,
          "4年前": 651
        }
      },
      "reporting_company": {
        "average_age_years": 39.7,
        "average_tenure_years": 13.8,
        "average_annual_salary_yen": 7260593
      },
      "diversity": {
        "scope": "提出会社",
        "female_manager_ratio": 0.027,
        "female_to_male_wage_ratio_all": 0.791,
        "female_to_male_wage_ratio_regular": 0.791,
        "female_to_male_wage_ratio_nonregular": null,
        "male_childcare_leave_ratio": 0.166,
        "male_childcare_leave_method": "原則方式"
      },
      "subsidiaries": [],
      "notes": [],
      "is_holding": false,
      "basis_change_note": "",
      "reorganization_note": ""
    }
  ],
  "salary_breaks": {},
  "headcount_breaks": {},
  "salary_trend_comparable": true,
  "headcount_trend_comparable": true,
  "trend": {
    "average_annual_salary_yen": {
      "2022-03-31": 6126630,
      "2023-03-31": 5850902,
      "2024-03-31": 5972385,
      "2025-03-31": 6146247,
      "2026-03-31": 7260593
    },
    "employees_reporting_company": {
      "2022-03-31": 312,
      "2023-03-31": 335,
      "2024-03-31": 358,
      "2025-03-31": 383,
      "2026-03-31": 362
    },
    "female_manager_ratio": {
      "2024-03-31": 0.032,
      "2025-03-31": 0.033,
      "2026-03-31": 0.027
    },
    "female_to_male_wage_ratio_all": {
      "2024-03-31": 0.703,
      "2025-03-31": 0.764,
      "2026-03-31": 0.791
    }
  }
}