{
  "edinet_code": "E00562",
  "name": "セーレン株式会社",
  "sec_code": "35690",
  "industry": "繊維製品",
  "peer_group": "繊維製品",
  "is_holding": false,
  "latest": {
    "source": {
      "doc_type": "有価証券報告書",
      "doc_id": "S100YH1G",
      "period_end": "2026-03-31",
      "submit_datetime": "2026-06-24 10:22",
      "description": "有価証券報告書－第154期(2025/04/01－2026/03/31)"
    },
    "employees": {
      "consolidated": 6506,
      "reporting_company": 1320,
      "reporting_company_source": "XBRL標準タグと一致",
      "reporting_company_xbrl_standard_tag": 1320,
      "consolidated_history": {
        "当期末": 6506,
        "1年前": 6228,
        "2年前": 6108,
        "3年前": 6200,
        "4年前": 6341
      }
    },
    "reporting_company": {
      "average_age_years": 43.86,
      "average_tenure_years": 19.71,
      "average_annual_salary_yen": 7140994
    },
    "diversity": {
      "scope": "提出会社",
      "female_manager_ratio": null,
      "female_to_male_wage_ratio_all": 0.781,
      "female_to_male_wage_ratio_regular": 0.829,
      "female_to_male_wage_ratio_nonregular": 0.91,
      "male_childcare_leave_ratio": 0.742,
      "male_childcare_leave_method": "71条の6第2号方式（育児目的休暇を含む）"
    },
    "subsidiaries": [],
    "notes": [
      "管理職に占める女性労働者の割合は有報に記載なし（非公表）。"
    ],
    "is_holding": false,
    "basis_change_note": "",
    "reorganization_note": ""
  },
  "years": [
    {
      "source": {
        "doc_type": "有価証券報告書",
        "doc_id": "S100OBXX",
        "period_end": "2022-03-31",
        "submit_datetime": "2022-06-22 10:20",
        "description": "有価証券報告書－第150期(令和3年4月1日－令和4年3月31日)"
      },
      "employees": {
        "consolidated": 6341,
        "reporting_company": 1464,
        "reporting_company_source": "XBRL標準タグと一致",
        "reporting_company_xbrl_standard_tag": 1464,
        "consolidated_history": {
          "当期末": 6341,
          "1年前": 5590,
          "2年前": 5786,
          "3年前": 5970,
          "4年前": 5445
        }
      },
      "reporting_company": {
        "average_age_years": 42.8,
        "average_tenure_years": 18.7,
        "average_annual_salary_yen": 6239852
      },
      "diversity": {
        "scope": null,
        "female_manager_ratio": null,
        "female_to_male_wage_ratio_all": null,
        "female_to_male_wage_ratio_regular": null,
        "female_to_male_wage_ratio_nonregular": null,
        "male_childcare_leave_ratio": null,
        "male_childcare_leave_method": null
      },
      "subsidiaries": [],
      "notes": [
        "多様性指標は有報に記載なし（非公表）。"
      ],
      "is_holding": false,
      "basis_change_note": "",
      "reorganization_note": ""
    },
    {
      "source": {
        "doc_type": "有価証券報告書",
        "doc_id": "S100QZ2B",
        "period_end": "2023-03-31",
        "submit_datetime": "2023-06-21 11:45",
        "description": "有価証券報告書－第151期(2022/04/01－2023/03/31)"
      },
      "employees": {
        "consolidated": 6200,
        "reporting_company": 1447,
        "reporting_company_source": "XBRL標準タグと一致",
        "reporting_company_xbrl_standard_tag": 1447,
        "consolidated_history": {
          "当期末": 6200,
          "1年前": 6341,
          "2年前": 5590,
          "3年前": 5786,
          "4年前": 5970
        }
      },
      "reporting_company": {
        "average_age_years": 43.4,
        "average_tenure_years": 19.2,
        "average_annual_salary_yen": 6351700
      },
      "diversity": {
        "scope": null,
        "female_manager_ratio": null,
        "female_to_male_wage_ratio_all": null,
        "female_to_male_wage_ratio_regular": null,
        "female_to_male_wage_ratio_nonregular": null,
        "male_childcare_leave_ratio": null,
        "male_childcare_leave_method": null
      },
      "subsidiaries": [],
      "notes": [
        "多様性指標は有報に記載なし（非公表）。"
      ],
      "is_holding": false,
      "basis_change_note": "",
      "reorganization_note": ""
    },
    {
      "source": {
        "doc_type": "有価証券報告書",
        "doc_id": "S100TOXY",
        "period_end": "2024-03-31",
        "submit_datetime": "2024-06-21 11:38",
        "description": "有価証券報告書－第152期(2023/04/01－2024/03/31)"
      },
      "employees": {
        "consolidated": 6108,
        "reporting_company": 1333,
        "reporting_company_source": "XBRL標準タグと一致",
        "reporting_company_xbrl_standard_tag": 1333,
        "consolidated_history": {
          "当期末": 6108,
          "1年前": 6200,
          "2年前": 6341,
          "3年前": 5590,
          "4年前": 5786
        }
      },
      "reporting_company": {
        "average_age_years": 43.8,
        "average_tenure_years": 19.6,
        "average_annual_salary_yen": 6618206
      },
      "diversity": {
        "scope": "提出会社",
        "female_manager_ratio": null,
        "female_to_male_wage_ratio_all": 0.774,
        "female_to_male_wage_ratio_regular": 0.826,
        "female_to_male_wage_ratio_nonregular": 0.936,
        "male_childcare_leave_ratio": 0.66,
        "male_childcare_leave_method": "71条の6第2号方式（育児目的休暇を含む）"
      },
      "subsidiaries": [],
      "notes": [
        "管理職に占める女性労働者の割合は有報に記載なし（非公表）。"
      ],
      "is_holding": false,
      "basis_change_note": "",
      "reorganization_note": ""
    },
    {
      "source": {
        "doc_type": "有価証券報告書",
        "doc_id": "S100W270",
        "period_end": "2025-03-31",
        "submit_datetime": "2025-06-25 13:23",
        "description": "有価証券報告書－第153期(2024/04/01－2025/03/31)"
      },
      "employees": {
        "consolidated": 6228,
        "reporting_company": 1317,
        "reporting_company_source": "XBRL標準タグと一致",
        "reporting_company_xbrl_standard_tag": 1317,
        "consolidated_history": {
          "当期末": 6228,
          "1年前": 6108,
          "2年前": 6200,
          "3年前": 6341,
          "4年前": 5590
        }
      },
      "reporting_company": {
        "average_age_years": 43.8,
        "average_tenure_years": 19.62,
        "average_annual_salary_yen": 6887802
      },
      "diversity": {
        "scope": "提出会社",
        "female_manager_ratio": null,
        "female_to_male_wage_ratio_all": 0.74,
        "female_to_male_wage_ratio_regular": 0.795,
        "female_to_male_wage_ratio_nonregular": 0.89,
        "male_childcare_leave_ratio": 0.806,
        "male_childcare_leave_method": "71条の6第2号方式（育児目的休暇を含む）"
      },
      "subsidiaries": [],
      "notes": [
        "管理職に占める女性労働者の割合は有報に記載なし（非公表）。"
      ],
      "is_holding": false,
      "basis_change_note": "",
      "reorganization_note": ""
    },
    {
      "source": {
        "doc_type": "有価証券報告書",
        "doc_id": "S100YH1G",
        "period_end": "2026-03-31",
        "submit_datetime": "2026-06-24 10:22",
        "description": "有価証券報告書－第154期(2025/04/01－2026/03/31)"
      },
      "employees": {
        "consolidated": 6506,
        "reporting_company": 1320,
        "reporting_company_source": "XBRL標準タグと一致",
        "reporting_company_xbrl_standard_tag": 1320,
        "consolidated_history": {
          "当期末": 6506,
          "1年前": 6228,
          "2年前": 6108,
          "3年前": 6200,
          "4年前": 6341
        }
      },
      "reporting_company": {
        "average_age_years": 43.86,
        "average_tenure_years": 19.71,
        "average_annual_salary_yen": 7140994
      },
      "diversity": {
        "scope": "提出会社",
        "female_manager_ratio": null,
        "female_to_male_wage_ratio_all": 0.781,
        "female_to_male_wage_ratio_regular": 0.829,
        "female_to_male_wage_ratio_nonregular": 0.91,
        "male_childcare_leave_ratio": 0.742,
        "male_childcare_leave_method": "71条の6第2号方式（育児目的休暇を含む）"
      },
      "subsidiaries": [],
      "notes": [
        "管理職に占める女性労働者の割合は有報に記載なし（非公表）。"
      ],
      "is_holding": false,
      "basis_change_note": "",
      "reorganization_note": ""
    }
  ],
  "salary_breaks": {},
  "headcount_breaks": {},
  "salary_trend_comparable": true,
  "headcount_trend_comparable": true,
  "trend": {
    "average_annual_salary_yen": {
      "2022-03-31": 6239852,
      "2023-03-31": 6351700,
      "2024-03-31": 6618206,
      "2025-03-31": 6887802,
      "2026-03-31": 7140994
    },
    "employees_reporting_company": {
      "2022-03-31": 1464,
      "2023-03-31": 1447,
      "2024-03-31": 1333,
      "2025-03-31": 1317,
      "2026-03-31": 1320
    },
    "female_manager_ratio": {},
    "female_to_male_wage_ratio_all": {
      "2024-03-31": 0.774,
      "2025-03-31": 0.74,
      "2026-03-31": 0.781
    }
  }
}