{
  "edinet_code": "E02516",
  "name": "ＫＰＰグループホールディングス株式会社",
  "sec_code": "92740",
  "industry": "卸売業",
  "peer_group": "卸売業",
  "is_holding": true,
  "latest": {
    "source": {
      "doc_type": "有価証券報告書",
      "doc_id": "S100YHDZ",
      "period_end": "2026-03-31",
      "submit_datetime": "2026-06-23 15:03",
      "description": "有価証券報告書－第152期(2025/04/01－2026/03/31)"
    },
    "employees": {
      "consolidated": 6024,
      "reporting_company": 36,
      "reporting_company_source": "XBRL標準タグと一致",
      "reporting_company_xbrl_standard_tag": 36,
      "consolidated_history": {
        "当期末": 6024,
        "1年前": 5974,
        "2年前": 5624,
        "3年前": 5457,
        "4年前": 5354
      }
    },
    "reporting_company": {
      "average_age_years": 46.5,
      "average_tenure_years": 9.3,
      "average_annual_salary_yen": 8727698
    },
    "diversity": {
      "scope": "提出会社",
      "female_manager_ratio": 0.23,
      "female_to_male_wage_ratio_all": 0.748,
      "female_to_male_wage_ratio_regular": 0.742,
      "female_to_male_wage_ratio_nonregular": null,
      "male_childcare_leave_ratio": 1.0,
      "male_childcare_leave_method": "原則方式"
    },
    "subsidiaries": [],
    "notes": [
      "提出会社は持株会社。平均年間給与・平均年齢・平均勤続年数は持株会社本体（36人）の数値であり、事業会社のものではない。"
    ],
    "is_holding": true,
    "basis_change_note": "",
    "reorganization_note": ""
  },
  "years": [
    {
      "source": {
        "doc_type": "有価証券報告書",
        "doc_id": "S100OKSC",
        "period_end": "2022-03-31",
        "submit_datetime": "2022-06-29 16:13",
        "description": "有価証券報告書－第148期(令和3年4月1日－令和4年3月31日)"
      },
      "employees": {
        "consolidated": 5354,
        "reporting_company": 607,
        "reporting_company_source": "XBRL標準タグと一致",
        "reporting_company_xbrl_standard_tag": 607,
        "consolidated_history": {
          "当期末": 5354,
          "1年前": 5530,
          "2年前": 1288,
          "3年前": 1005,
          "4年前": 956
        }
      },
      "reporting_company": {
        "average_age_years": 42.7,
        "average_tenure_years": 17.9,
        "average_annual_salary_yen": 7173426
      },
      "diversity": {
        "scope": null,
        "female_manager_ratio": null,
        "female_to_male_wage_ratio_all": null,
        "female_to_male_wage_ratio_regular": null,
        "female_to_male_wage_ratio_nonregular": null,
        "male_childcare_leave_ratio": null,
        "male_childcare_leave_method": null
      },
      "subsidiaries": [],
      "notes": [
        "多様性指標は有報に記載なし（非公表）。",
        "提出会社は持株会社。平均年間給与・平均年齢・平均勤続年数は持株会社本体（607人）の数値であり、事業会社のものではない。"
      ],
      "is_holding": true,
      "basis_change_note": "",
      "reorganization_note": ""
    },
    {
      "source": {
        "doc_type": "有価証券報告書",
        "doc_id": "S100R8VM",
        "period_end": "2023-03-31",
        "submit_datetime": "2023-06-29 15:47",
        "description": "有価証券報告書－第149期(2022/04/01－2023/03/31)"
      },
      "employees": {
        "consolidated": 5457,
        "reporting_company": 52,
        "reporting_company_source": "XBRL標準タグと一致",
        "reporting_company_xbrl_standard_tag": 52,
        "consolidated_history": {
          "当期末": 5457,
          "1年前": 5354,
          "2年前": 5530,
          "3年前": 1288,
          "4年前": 1005
        }
      },
      "reporting_company": {
        "average_age_years": 45.5,
        "average_tenure_years": 12.8,
        "average_annual_salary_yen": 8539773
      },
      "diversity": {
        "scope": null,
        "female_manager_ratio": null,
        "female_to_male_wage_ratio_all": null,
        "female_to_male_wage_ratio_regular": null,
        "female_to_male_wage_ratio_nonregular": null,
        "male_childcare_leave_ratio": null,
        "male_childcare_leave_method": null
      },
      "subsidiaries": [],
      "notes": [
        "多様性指標は有報に記載なし（非公表）。",
        "提出会社は持株会社。平均年間給与・平均年齢・平均勤続年数は持株会社本体（52人）の数値であり、事業会社のものではない。"
      ],
      "is_holding": true,
      "basis_change_note": "",
      "reorganization_note": ""
    },
    {
      "source": {
        "doc_type": "有価証券報告書",
        "doc_id": "S100TW1P",
        "period_end": "2024-03-31",
        "submit_datetime": "2024-06-27 15:09",
        "description": "有価証券報告書－第150期(2023/04/01－2024/03/31)"
      },
      "employees": {
        "consolidated": 5624,
        "reporting_company": 52,
        "reporting_company_source": "XBRL標準タグと一致",
        "reporting_company_xbrl_standard_tag": 52,
        "consolidated_history": {
          "当期末": 5624,
          "1年前": 5457,
          "2年前": 5354,
          "3年前": 5530,
          "4年前": 1288
        }
      },
      "reporting_company": {
        "average_age_years": 46.1,
        "average_tenure_years": 12.0,
        "average_annual_salary_yen": 9213044
      },
      "diversity": {
        "scope": "提出会社",
        "female_manager_ratio": 0.136,
        "female_to_male_wage_ratio_all": 0.66,
        "female_to_male_wage_ratio_regular": 0.612,
        "female_to_male_wage_ratio_nonregular": null,
        "male_childcare_leave_ratio": 0.0,
        "male_childcare_leave_method": "原則方式"
      },
      "subsidiaries": [],
      "notes": [
        "提出会社は持株会社。平均年間給与・平均年齢・平均勤続年数は持株会社本体（52人）の数値であり、事業会社のものではない。"
      ],
      "is_holding": true,
      "basis_change_note": "",
      "reorganization_note": ""
    },
    {
      "source": {
        "doc_type": "有価証券報告書",
        "doc_id": "S100W4SL",
        "period_end": "2025-03-31",
        "submit_datetime": "2025-06-25 15:25",
        "description": "有価証券報告書－第151期(2024/04/01－2025/03/31)"
      },
      "employees": {
        "consolidated": 5974,
        "reporting_company": 34,
        "reporting_company_source": "XBRL標準タグと一致",
        "reporting_company_xbrl_standard_tag": 34,
        "consolidated_history": {
          "当期末": 5974,
          "1年前": 5624,
          "2年前": 5457,
          "3年前": 5354,
          "4年前": 5530
        }
      },
      "reporting_company": {
        "average_age_years": 44.8,
        "average_tenure_years": 9.6,
        "average_annual_salary_yen": 9361201
      },
      "diversity": {
        "scope": "提出会社",
        "female_manager_ratio": 0.167,
        "female_to_male_wage_ratio_all": 0.693,
        "female_to_male_wage_ratio_regular": 0.681,
        "female_to_male_wage_ratio_nonregular": null,
        "male_childcare_leave_ratio": 0.0,
        "male_childcare_leave_method": "原則方式"
      },
      "subsidiaries": [],
      "notes": [
        "提出会社は持株会社。平均年間給与・平均年齢・平均勤続年数は持株会社本体（34人）の数値であり、事業会社のものではない。"
      ],
      "is_holding": true,
      "basis_change_note": "",
      "reorganization_note": ""
    },
    {
      "source": {
        "doc_type": "有価証券報告書",
        "doc_id": "S100YHDZ",
        "period_end": "2026-03-31",
        "submit_datetime": "2026-06-23 15:03",
        "description": "有価証券報告書－第152期(2025/04/01－2026/03/31)"
      },
      "employees": {
        "consolidated": 6024,
        "reporting_company": 36,
        "reporting_company_source": "XBRL標準タグと一致",
        "reporting_company_xbrl_standard_tag": 36,
        "consolidated_history": {
          "当期末": 6024,
          "1年前": 5974,
          "2年前": 5624,
          "3年前": 5457,
          "4年前": 5354
        }
      },
      "reporting_company": {
        "average_age_years": 46.5,
        "average_tenure_years": 9.3,
        "average_annual_salary_yen": 8727698
      },
      "diversity": {
        "scope": "提出会社",
        "female_manager_ratio": 0.23,
        "female_to_male_wage_ratio_all": 0.748,
        "female_to_male_wage_ratio_regular": 0.742,
        "female_to_male_wage_ratio_nonregular": null,
        "male_childcare_leave_ratio": 1.0,
        "male_childcare_leave_method": "原則方式"
      },
      "subsidiaries": [],
      "notes": [
        "提出会社は持株会社。平均年間給与・平均年齢・平均勤続年数は持株会社本体（36人）の数値であり、事業会社のものではない。"
      ],
      "is_holding": true,
      "basis_change_note": "",
      "reorganization_note": ""
    }
  ],
  "salary_breaks": {},
  "headcount_breaks": {},
  "salary_trend_comparable": true,
  "headcount_trend_comparable": true,
  "trend": {
    "average_annual_salary_yen": {
      "2022-03-31": 7173426,
      "2023-03-31": 8539773,
      "2024-03-31": 9213044,
      "2025-03-31": 9361201,
      "2026-03-31": 8727698
    },
    "employees_reporting_company": {
      "2022-03-31": 607,
      "2023-03-31": 52,
      "2024-03-31": 52,
      "2025-03-31": 34,
      "2026-03-31": 36
    },
    "female_manager_ratio": {
      "2024-03-31": 0.136,
      "2025-03-31": 0.167,
      "2026-03-31": 0.23
    },
    "female_to_male_wage_ratio_all": {
      "2024-03-31": 0.66,
      "2025-03-31": 0.693,
      "2026-03-31": 0.748
    }
  }
}