{
  "edinet_code": "E03563",
  "name": "株式会社八十二長野銀行",
  "sec_code": "83590",
  "industry": "銀行業",
  "peer_group": "銀行業",
  "is_holding": false,
  "latest": {
    "source": {
      "doc_type": "有価証券報告書",
      "doc_id": "S100YAUN",
      "period_end": "2026-03-31",
      "submit_datetime": "2026-06-16 09:10",
      "description": "有価証券報告書－第143期(2025/04/01－2026/03/31)"
    },
    "employees": {
      "consolidated": 4128,
      "reporting_company": 3773,
      "reporting_company_source": "XBRL標準タグと一致",
      "reporting_company_xbrl_standard_tag": 3773,
      "consolidated_history": {
        "当期末": 4128,
        "1年前": 4121,
        "2年前": 4140,
        "3年前": 3531,
        "4年前": 3569
      }
    },
    "reporting_company": {
      "average_age_years": 42.1,
      "average_tenure_years": 15.5,
      "average_annual_salary_yen": 8082000
    },
    "diversity": {
      "scope": "提出会社",
      "female_manager_ratio": 0.146,
      "female_to_male_wage_ratio_all": 0.501,
      "female_to_male_wage_ratio_regular": 0.582,
      "female_to_male_wage_ratio_nonregular": 0.538,
      "male_childcare_leave_ratio": 0.981,
      "male_childcare_leave_method": "71条の6第2号方式（育児目的休暇を含む）"
    },
    "subsidiaries": [],
    "notes": [],
    "is_holding": false,
    "basis_change_note": "",
    "reorganization_note": ""
  },
  "years": [
    {
      "source": {
        "doc_type": "有価証券報告書",
        "doc_id": "S100OBUG",
        "period_end": "2022-03-31",
        "submit_datetime": "2022-06-27 09:35",
        "description": "有価証券報告書－第139期(令和3年4月1日－令和4年3月31日)"
      },
      "employees": {
        "consolidated": 3569,
        "reporting_company": 2966,
        "reporting_company_source": "XBRL標準タグと一致",
        "reporting_company_xbrl_standard_tag": 2966,
        "consolidated_history": {
          "当期末": 3569,
          "1年前": 3689,
          "2年前": 3669,
          "3年前": 3713,
          "4年前": 3710
        }
      },
      "reporting_company": {
        "average_age_years": 42.2,
        "average_tenure_years": 15.9,
        "average_annual_salary_yen": 6495000
      },
      "diversity": {
        "scope": null,
        "female_manager_ratio": null,
        "female_to_male_wage_ratio_all": null,
        "female_to_male_wage_ratio_regular": null,
        "female_to_male_wage_ratio_nonregular": null,
        "male_childcare_leave_ratio": null,
        "male_childcare_leave_method": null
      },
      "subsidiaries": [],
      "notes": [
        "多様性指標は有報に記載なし（非公表）。"
      ],
      "is_holding": false,
      "basis_change_note": "",
      "reorganization_note": ""
    },
    {
      "source": {
        "doc_type": "有価証券報告書",
        "doc_id": "S100R0C5",
        "period_end": "2023-03-31",
        "submit_datetime": "2023-06-26 09:15",
        "description": "有価証券報告書－第140期(2022/04/01－2023/03/31)"
      },
      "employees": {
        "consolidated": 3531,
        "reporting_company": 2942,
        "reporting_company_source": "XBRL標準タグと一致",
        "reporting_company_xbrl_standard_tag": 2942,
        "consolidated_history": {
          "当期末": 3531,
          "1年前": 3569,
          "2年前": 3689,
          "3年前": 3669,
          "4年前": 3713
        }
      },
      "reporting_company": {
        "average_age_years": 42.1,
        "average_tenure_years": 15.7,
        "average_annual_salary_yen": 6715000
      },
      "diversity": {
        "scope": null,
        "female_manager_ratio": null,
        "female_to_male_wage_ratio_all": null,
        "female_to_male_wage_ratio_regular": null,
        "female_to_male_wage_ratio_nonregular": null,
        "male_childcare_leave_ratio": null,
        "male_childcare_leave_method": null
      },
      "subsidiaries": [],
      "notes": [
        "多様性指標は有報に記載なし（非公表）。"
      ],
      "is_holding": false,
      "basis_change_note": "",
      "reorganization_note": ""
    },
    {
      "source": {
        "doc_type": "有価証券報告書",
        "doc_id": "S100TPHV",
        "period_end": "2024-03-31",
        "submit_datetime": "2024-06-24 13:19",
        "description": "有価証券報告書－第141期(2023/04/01－2024/03/31)"
      },
      "employees": {
        "consolidated": 4140,
        "reporting_company": 3195,
        "reporting_company_source": "XBRL標準タグと一致",
        "reporting_company_xbrl_standard_tag": 3195,
        "consolidated_history": {
          "当期末": 4140,
          "1年前": 3531,
          "2年前": 3569,
          "3年前": 3689,
          "4年前": 3669
        }
      },
      "reporting_company": {
        "average_age_years": 42.1,
        "average_tenure_years": 14.5,
        "average_annual_salary_yen": 6913000
      },
      "diversity": {
        "scope": "提出会社",
        "female_manager_ratio": 0.133,
        "female_to_male_wage_ratio_all": 0.462,
        "female_to_male_wage_ratio_regular": 0.547,
        "female_to_male_wage_ratio_nonregular": 0.568,
        "male_childcare_leave_ratio": 1.019,
        "male_childcare_leave_method": "71条の6第2号方式（育児目的休暇を含む）"
      },
      "subsidiaries": [],
      "notes": [],
      "is_holding": false,
      "basis_change_note": "",
      "reorganization_note": ""
    },
    {
      "source": {
        "doc_type": "有価証券報告書",
        "doc_id": "S100VXML",
        "period_end": "2025-03-31",
        "submit_datetime": "2025-06-17 09:09",
        "description": "有価証券報告書－第142期(2024/04/01－2025/03/31)"
      },
      "employees": {
        "consolidated": 4121,
        "reporting_company": 3482,
        "reporting_company_source": "XBRL標準タグと一致",
        "reporting_company_xbrl_standard_tag": 3482,
        "consolidated_history": {
          "当期末": 4121,
          "1年前": 4140,
          "2年前": 3531,
          "3年前": 3569,
          "4年前": 3689
        }
      },
      "reporting_company": {
        "average_age_years": 42.4,
        "average_tenure_years": 14.5,
        "average_annual_salary_yen": 8191000
      },
      "diversity": {
        "scope": "提出会社",
        "female_manager_ratio": 0.145,
        "female_to_male_wage_ratio_all": 0.473,
        "female_to_male_wage_ratio_regular": 0.567,
        "female_to_male_wage_ratio_nonregular": 0.496,
        "male_childcare_leave_ratio": 0.952,
        "male_childcare_leave_method": "71条の6第2号方式（育児目的休暇を含む）"
      },
      "subsidiaries": [],
      "notes": [],
      "is_holding": false,
      "basis_change_note": "",
      "reorganization_note": ""
    },
    {
      "source": {
        "doc_type": "有価証券報告書",
        "doc_id": "S100YAUN",
        "period_end": "2026-03-31",
        "submit_datetime": "2026-06-16 09:10",
        "description": "有価証券報告書－第143期(2025/04/01－2026/03/31)"
      },
      "employees": {
        "consolidated": 4128,
        "reporting_company": 3773,
        "reporting_company_source": "XBRL標準タグと一致",
        "reporting_company_xbrl_standard_tag": 3773,
        "consolidated_history": {
          "当期末": 4128,
          "1年前": 4121,
          "2年前": 4140,
          "3年前": 3531,
          "4年前": 3569
        }
      },
      "reporting_company": {
        "average_age_years": 42.1,
        "average_tenure_years": 15.5,
        "average_annual_salary_yen": 8082000
      },
      "diversity": {
        "scope": "提出会社",
        "female_manager_ratio": 0.146,
        "female_to_male_wage_ratio_all": 0.501,
        "female_to_male_wage_ratio_regular": 0.582,
        "female_to_male_wage_ratio_nonregular": 0.538,
        "male_childcare_leave_ratio": 0.981,
        "male_childcare_leave_method": "71条の6第2号方式（育児目的休暇を含む）"
      },
      "subsidiaries": [],
      "notes": [],
      "is_holding": false,
      "basis_change_note": "",
      "reorganization_note": ""
    }
  ],
  "salary_breaks": {},
  "headcount_breaks": {},
  "salary_trend_comparable": true,
  "headcount_trend_comparable": true,
  "trend": {
    "average_annual_salary_yen": {
      "2022-03-31": 6495000,
      "2023-03-31": 6715000,
      "2024-03-31": 6913000,
      "2025-03-31": 8191000,
      "2026-03-31": 8082000
    },
    "employees_reporting_company": {
      "2022-03-31": 2966,
      "2023-03-31": 2942,
      "2024-03-31": 3195,
      "2025-03-31": 3482,
      "2026-03-31": 3773
    },
    "female_manager_ratio": {
      "2024-03-31": 0.133,
      "2025-03-31": 0.145,
      "2026-03-31": 0.146
    },
    "female_to_male_wage_ratio_all": {
      "2024-03-31": 0.462,
      "2025-03-31": 0.473,
      "2026-03-31": 0.501
    }
  }
}