{
  "edinet_code": "E05025",
  "name": "株式会社オービック",
  "sec_code": "46840",
  "industry": "情報・通信業",
  "peer_group": "情報・通信業",
  "is_holding": false,
  "latest": {
    "source": {
      "doc_type": "有価証券報告書",
      "doc_id": "S100YGBS",
      "period_end": "2026-03-31",
      "submit_datetime": "2026-06-23 10:00",
      "description": "有価証券報告書－第59期(2025/04/01－2026/03/31)"
    },
    "employees": {
      "consolidated": 2256,
      "reporting_company": 2030,
      "reporting_company_source": "XBRL標準タグと一致",
      "reporting_company_xbrl_standard_tag": 2030,
      "consolidated_history": {
        "当期末": 2256,
        "1年前": 2189,
        "2年前": 2107,
        "3年前": 2082,
        "4年前": 2054
      }
    },
    "reporting_company": {
      "average_age_years": 35.8,
      "average_tenure_years": 12.9,
      "average_annual_salary_yen": 11292000
    },
    "diversity": {
      "scope": "提出会社",
      "female_manager_ratio": 0.146,
      "female_to_male_wage_ratio_all": 0.765,
      "female_to_male_wage_ratio_regular": 0.771,
      "female_to_male_wage_ratio_nonregular": 0.735,
      "male_childcare_leave_ratio": 1.014,
      "male_childcare_leave_method": "71条の6第2号方式（育児目的休暇を含む）"
    },
    "subsidiaries": [],
    "notes": [],
    "is_holding": false,
    "basis_change_note": "",
    "reorganization_note": ""
  },
  "years": [
    {
      "source": {
        "doc_type": "有価証券報告書",
        "doc_id": "S100OF9D",
        "period_end": "2022-03-31",
        "submit_datetime": "2022-06-30 09:28",
        "description": "有価証券報告書－第55期(令和3年4月1日－令和4年3月31日)"
      },
      "employees": {
        "consolidated": 2054,
        "reporting_company": 1857,
        "reporting_company_source": "XBRL標準タグと一致",
        "reporting_company_xbrl_standard_tag": 1857,
        "consolidated_history": {
          "当期末": 2054,
          "1年前": 2049,
          "2年前": 2051,
          "3年前": 2058,
          "4年前": 2034
        }
      },
      "reporting_company": {
        "average_age_years": 36.2,
        "average_tenure_years": 13.2,
        "average_annual_salary_yen": 9596000
      },
      "diversity": {
        "scope": null,
        "female_manager_ratio": null,
        "female_to_male_wage_ratio_all": null,
        "female_to_male_wage_ratio_regular": null,
        "female_to_male_wage_ratio_nonregular": null,
        "male_childcare_leave_ratio": null,
        "male_childcare_leave_method": null
      },
      "subsidiaries": [],
      "notes": [
        "多様性指標は有報に記載なし（非公表）。"
      ],
      "is_holding": false,
      "basis_change_note": "",
      "reorganization_note": ""
    },
    {
      "source": {
        "doc_type": "有価証券報告書",
        "doc_id": "S100R4R5",
        "period_end": "2023-03-31",
        "submit_datetime": "2023-06-30 09:10",
        "description": "有価証券報告書－第56期(2022/04/01－2023/03/31)"
      },
      "employees": {
        "consolidated": 2082,
        "reporting_company": 1888,
        "reporting_company_source": "XBRL標準タグと一致",
        "reporting_company_xbrl_standard_tag": 1888,
        "consolidated_history": {
          "当期末": 2082,
          "1年前": 2054,
          "2年前": 2049,
          "3年前": 2051,
          "4年前": 2058
        }
      },
      "reporting_company": {
        "average_age_years": 36.1,
        "average_tenure_years": 13.2,
        "average_annual_salary_yen": 10056000
      },
      "diversity": {
        "scope": null,
        "female_manager_ratio": null,
        "female_to_male_wage_ratio_all": null,
        "female_to_male_wage_ratio_regular": null,
        "female_to_male_wage_ratio_nonregular": null,
        "male_childcare_leave_ratio": null,
        "male_childcare_leave_method": null
      },
      "subsidiaries": [],
      "notes": [
        "多様性指標は有報に記載なし（非公表）。"
      ],
      "is_holding": false,
      "basis_change_note": "",
      "reorganization_note": ""
    },
    {
      "source": {
        "doc_type": "有価証券報告書",
        "doc_id": "S100TVPX",
        "period_end": "2024-03-31",
        "submit_datetime": "2024-06-28 09:59",
        "description": "有価証券報告書－第57期(2023/04/01－2024/03/31)"
      },
      "employees": {
        "consolidated": 2107,
        "reporting_company": 1898,
        "reporting_company_source": "XBRL標準タグと一致",
        "reporting_company_xbrl_standard_tag": 1898,
        "consolidated_history": {
          "当期末": 2107,
          "1年前": 2082,
          "2年前": 2054,
          "3年前": 2049,
          "4年前": 2051
        }
      },
      "reporting_company": {
        "average_age_years": 36.1,
        "average_tenure_years": 13.2,
        "average_annual_salary_yen": 10780000
      },
      "diversity": {
        "scope": "提出会社",
        "female_manager_ratio": 0.112,
        "female_to_male_wage_ratio_all": 0.752,
        "female_to_male_wage_ratio_regular": 0.76,
        "female_to_male_wage_ratio_nonregular": 0.755,
        "male_childcare_leave_ratio": 0.862,
        "male_childcare_leave_method": "71条の6第2号方式（育児目的休暇を含む）"
      },
      "subsidiaries": [],
      "notes": [],
      "is_holding": false,
      "basis_change_note": "",
      "reorganization_note": ""
    },
    {
      "source": {
        "doc_type": "有価証券報告書",
        "doc_id": "S100W1Y7",
        "period_end": "2025-03-31",
        "submit_datetime": "2025-06-24 10:00",
        "description": "有価証券報告書－第58期(2024/04/01－2025/03/31)"
      },
      "employees": {
        "consolidated": 2189,
        "reporting_company": 1969,
        "reporting_company_source": "XBRL標準タグと一致",
        "reporting_company_xbrl_standard_tag": 1969,
        "consolidated_history": {
          "当期末": 2189,
          "1年前": 2107,
          "2年前": 2082,
          "3年前": 2054,
          "4年前": 2049
        }
      },
      "reporting_company": {
        "average_age_years": 35.9,
        "average_tenure_years": 13.0,
        "average_annual_salary_yen": 11031000
      },
      "diversity": {
        "scope": "提出会社",
        "female_manager_ratio": 0.128,
        "female_to_male_wage_ratio_all": 0.761,
        "female_to_male_wage_ratio_regular": 0.768,
        "female_to_male_wage_ratio_nonregular": 0.747,
        "male_childcare_leave_ratio": 0.968,
        "male_childcare_leave_method": "71条の6第2号方式（育児目的休暇を含む）"
      },
      "subsidiaries": [],
      "notes": [],
      "is_holding": false,
      "basis_change_note": "",
      "reorganization_note": ""
    },
    {
      "source": {
        "doc_type": "有価証券報告書",
        "doc_id": "S100YGBS",
        "period_end": "2026-03-31",
        "submit_datetime": "2026-06-23 10:00",
        "description": "有価証券報告書－第59期(2025/04/01－2026/03/31)"
      },
      "employees": {
        "consolidated": 2256,
        "reporting_company": 2030,
        "reporting_company_source": "XBRL標準タグと一致",
        "reporting_company_xbrl_standard_tag": 2030,
        "consolidated_history": {
          "当期末": 2256,
          "1年前": 2189,
          "2年前": 2107,
          "3年前": 2082,
          "4年前": 2054
        }
      },
      "reporting_company": {
        "average_age_years": 35.8,
        "average_tenure_years": 12.9,
        "average_annual_salary_yen": 11292000
      },
      "diversity": {
        "scope": "提出会社",
        "female_manager_ratio": 0.146,
        "female_to_male_wage_ratio_all": 0.765,
        "female_to_male_wage_ratio_regular": 0.771,
        "female_to_male_wage_ratio_nonregular": 0.735,
        "male_childcare_leave_ratio": 1.014,
        "male_childcare_leave_method": "71条の6第2号方式（育児目的休暇を含む）"
      },
      "subsidiaries": [],
      "notes": [],
      "is_holding": false,
      "basis_change_note": "",
      "reorganization_note": ""
    }
  ],
  "salary_breaks": {},
  "headcount_breaks": {},
  "salary_trend_comparable": true,
  "headcount_trend_comparable": true,
  "trend": {
    "average_annual_salary_yen": {
      "2022-03-31": 9596000,
      "2023-03-31": 10056000,
      "2024-03-31": 10780000,
      "2025-03-31": 11031000,
      "2026-03-31": 11292000
    },
    "employees_reporting_company": {
      "2022-03-31": 1857,
      "2023-03-31": 1888,
      "2024-03-31": 1898,
      "2025-03-31": 1969,
      "2026-03-31": 2030
    },
    "female_manager_ratio": {
      "2024-03-31": 0.112,
      "2025-03-31": 0.128,
      "2026-03-31": 0.146
    },
    "female_to_male_wage_ratio_all": {
      "2024-03-31": 0.752,
      "2025-03-31": 0.761,
      "2026-03-31": 0.765
    }
  }
}