{
  "edinet_code": "E05419",
  "name": "株式会社キャリアデザインセンター",
  "sec_code": "24100",
  "industry": "サービス業",
  "peer_group": "サービス業",
  "is_holding": false,
  "latest": {
    "source": {
      "doc_type": "有価証券報告書",
      "doc_id": "S100XBEJ",
      "period_end": "2025-09-30",
      "submit_datetime": "2025-12-18 16:00",
      "description": "有価証券報告書－第34期(2024/10/01－2025/09/30)"
    },
    "employees": {
      "consolidated": null,
      "reporting_company": 768,
      "reporting_company_source": "XBRL標準タグと一致",
      "reporting_company_xbrl_standard_tag": 768,
      "consolidated_history": {}
    },
    "reporting_company": {
      "average_age_years": 30.7,
      "average_tenure_years": 5.9,
      "average_annual_salary_yen": 5514000
    },
    "diversity": {
      "scope": "提出会社",
      "female_manager_ratio": 0.487,
      "female_to_male_wage_ratio_all": 0.79,
      "female_to_male_wage_ratio_regular": 0.816,
      "female_to_male_wage_ratio_nonregular": 0.762,
      "male_childcare_leave_ratio": 0.2,
      "male_childcare_leave_method": "原則方式"
    },
    "subsidiaries": [],
    "notes": [],
    "is_holding": false,
    "basis_change_note": "",
    "reorganization_note": ""
  },
  "years": [
    {
      "source": {
        "doc_type": "有価証券報告書",
        "doc_id": "S100N2VN",
        "period_end": "2021-09-30",
        "submit_datetime": "2021-12-20 15:01",
        "description": "有価証券報告書－第30期(令和2年10月1日－令和3年9月30日)"
      },
      "employees": {
        "consolidated": null,
        "reporting_company": 662,
        "reporting_company_source": "XBRL標準タグと一致",
        "reporting_company_xbrl_standard_tag": 662,
        "consolidated_history": {
          "1年前": 660,
          "2年前": 651,
          "3年前": 605,
          "4年前": 581
        }
      },
      "reporting_company": {
        "average_age_years": 30.1,
        "average_tenure_years": 5.4,
        "average_annual_salary_yen": 5032000
      },
      "diversity": {
        "scope": null,
        "female_manager_ratio": null,
        "female_to_male_wage_ratio_all": null,
        "female_to_male_wage_ratio_regular": null,
        "female_to_male_wage_ratio_nonregular": null,
        "male_childcare_leave_ratio": null,
        "male_childcare_leave_method": null
      },
      "subsidiaries": [],
      "notes": [
        "多様性指標は有報に記載なし（非公表）。"
      ],
      "is_holding": false,
      "basis_change_note": "",
      "reorganization_note": ""
    },
    {
      "source": {
        "doc_type": "有価証券報告書",
        "doc_id": "S100PTMC",
        "period_end": "2022-09-30",
        "submit_datetime": "2022-12-19 15:01",
        "description": "有価証券報告書－第31期(令和3年10月1日－令和4年9月30日)"
      },
      "employees": {
        "consolidated": null,
        "reporting_company": 695,
        "reporting_company_source": "XBRL標準タグと一致",
        "reporting_company_xbrl_standard_tag": 695,
        "consolidated_history": {
          "2年前": 660,
          "3年前": 651,
          "4年前": 605
        }
      },
      "reporting_company": {
        "average_age_years": 30.4,
        "average_tenure_years": 5.5,
        "average_annual_salary_yen": 5446000
      },
      "diversity": {
        "scope": null,
        "female_manager_ratio": null,
        "female_to_male_wage_ratio_all": null,
        "female_to_male_wage_ratio_regular": null,
        "female_to_male_wage_ratio_nonregular": null,
        "male_childcare_leave_ratio": null,
        "male_childcare_leave_method": null
      },
      "subsidiaries": [],
      "notes": [
        "多様性指標は有報に記載なし（非公表）。"
      ],
      "is_holding": false,
      "basis_change_note": "",
      "reorganization_note": ""
    },
    {
      "source": {
        "doc_type": "有価証券報告書",
        "doc_id": "S100SHAF",
        "period_end": "2023-09-30",
        "submit_datetime": "2023-12-18 15:00",
        "description": "有価証券報告書－第32期(2022/10/01－2023/09/30)"
      },
      "employees": {
        "consolidated": null,
        "reporting_company": 783,
        "reporting_company_source": "XBRL標準タグと一致",
        "reporting_company_xbrl_standard_tag": 783,
        "consolidated_history": {
          "3年前": 660,
          "4年前": 651
        }
      },
      "reporting_company": {
        "average_age_years": 30.0,
        "average_tenure_years": 5.2,
        "average_annual_salary_yen": 5559000
      },
      "diversity": {
        "scope": null,
        "female_manager_ratio": null,
        "female_to_male_wage_ratio_all": null,
        "female_to_male_wage_ratio_regular": null,
        "female_to_male_wage_ratio_nonregular": null,
        "male_childcare_leave_ratio": null,
        "male_childcare_leave_method": null
      },
      "subsidiaries": [],
      "notes": [
        "多様性指標は有報に記載なし（非公表）。"
      ],
      "is_holding": false,
      "basis_change_note": "",
      "reorganization_note": ""
    },
    {
      "source": {
        "doc_type": "有価証券報告書",
        "doc_id": "S100UZRF",
        "period_end": "2024-09-30",
        "submit_datetime": "2024-12-23 15:31",
        "description": "有価証券報告書－第33期(2023/10/01－2024/09/30)"
      },
      "employees": {
        "consolidated": null,
        "reporting_company": 835,
        "reporting_company_source": "XBRL標準タグと一致",
        "reporting_company_xbrl_standard_tag": 835,
        "consolidated_history": {
          "4年前": 660
        }
      },
      "reporting_company": {
        "average_age_years": 30.1,
        "average_tenure_years": 5.3,
        "average_annual_salary_yen": 5497000
      },
      "diversity": {
        "scope": "提出会社",
        "female_manager_ratio": 0.487,
        "female_to_male_wage_ratio_all": 0.794,
        "female_to_male_wage_ratio_regular": 0.8,
        "female_to_male_wage_ratio_nonregular": 0.882,
        "male_childcare_leave_ratio": 0.111,
        "male_childcare_leave_method": "原則方式"
      },
      "subsidiaries": [],
      "notes": [],
      "is_holding": false,
      "basis_change_note": "",
      "reorganization_note": ""
    },
    {
      "source": {
        "doc_type": "有価証券報告書",
        "doc_id": "S100XBEJ",
        "period_end": "2025-09-30",
        "submit_datetime": "2025-12-18 16:00",
        "description": "有価証券報告書－第34期(2024/10/01－2025/09/30)"
      },
      "employees": {
        "consolidated": null,
        "reporting_company": 768,
        "reporting_company_source": "XBRL標準タグと一致",
        "reporting_company_xbrl_standard_tag": 768,
        "consolidated_history": {}
      },
      "reporting_company": {
        "average_age_years": 30.7,
        "average_tenure_years": 5.9,
        "average_annual_salary_yen": 5514000
      },
      "diversity": {
        "scope": "提出会社",
        "female_manager_ratio": 0.487,
        "female_to_male_wage_ratio_all": 0.79,
        "female_to_male_wage_ratio_regular": 0.816,
        "female_to_male_wage_ratio_nonregular": 0.762,
        "male_childcare_leave_ratio": 0.2,
        "male_childcare_leave_method": "原則方式"
      },
      "subsidiaries": [],
      "notes": [],
      "is_holding": false,
      "basis_change_note": "",
      "reorganization_note": ""
    }
  ],
  "salary_breaks": {},
  "headcount_breaks": {},
  "salary_trend_comparable": true,
  "headcount_trend_comparable": true,
  "trend": {
    "average_annual_salary_yen": {
      "2021-09-30": 5032000,
      "2022-09-30": 5446000,
      "2023-09-30": 5559000,
      "2024-09-30": 5497000,
      "2025-09-30": 5514000
    },
    "employees_reporting_company": {
      "2021-09-30": 662,
      "2022-09-30": 695,
      "2023-09-30": 783,
      "2024-09-30": 835,
      "2025-09-30": 768
    },
    "female_manager_ratio": {
      "2024-09-30": 0.487,
      "2025-09-30": 0.487
    },
    "female_to_male_wage_ratio_all": {
      "2024-09-30": 0.794,
      "2025-09-30": 0.79
    }
  }
}