{
  "edinet_code": "E05729",
  "name": "株式会社パソナグループ",
  "sec_code": "21680",
  "industry": "サービス業",
  "peer_group": "サービス業",
  "is_holding": false,
  "latest": {
    "source": {
      "doc_type": "有価証券報告書",
      "doc_id": "S100WJZQ",
      "period_end": "2025-05-31",
      "submit_datetime": "2025-08-20 09:00",
      "description": "有価証券報告書－第18期(2024/06/01－2025/05/31)"
    },
    "employees": {
      "consolidated": 8894,
      "reporting_company": 880,
      "reporting_company_source": "XBRL標準タグと一致",
      "reporting_company_xbrl_standard_tag": 880,
      "consolidated_history": {
        "当期末": 8894,
        "1年前": 10001,
        "2年前": 9786,
        "3年前": 10364,
        "4年前": 9498
      }
    },
    "reporting_company": {
      "average_age_years": 34.9,
      "average_tenure_years": 7.7,
      "average_annual_salary_yen": 6289000
    },
    "diversity": {
      "scope": "提出会社",
      "female_manager_ratio": 0.557,
      "female_to_male_wage_ratio_all": 0.856,
      "female_to_male_wage_ratio_regular": 0.848,
      "female_to_male_wage_ratio_nonregular": 0.828,
      "male_childcare_leave_ratio": 0.917,
      "male_childcare_leave_method": "原則方式"
    },
    "subsidiaries": [],
    "notes": [],
    "is_holding": false,
    "basis_change_note": "",
    "reorganization_note": ""
  },
  "years": [
    {
      "source": {
        "doc_type": "有価証券報告書",
        "doc_id": "S100MB9N",
        "period_end": "2021-05-31",
        "submit_datetime": "2021-08-23 15:30",
        "description": "有価証券報告書－第14期(令和2年6月1日－令和3年5月31日)"
      },
      "employees": {
        "consolidated": 9498,
        "reporting_company": 645,
        "reporting_company_source": "XBRL標準タグと一致",
        "reporting_company_xbrl_standard_tag": 645,
        "consolidated_history": {
          "当期末": 9498,
          "1年前": 9657,
          "2年前": 7855,
          "3年前": 7716,
          "4年前": 7238
        }
      },
      "reporting_company": {
        "average_age_years": 37.9,
        "average_tenure_years": 9.1,
        "average_annual_salary_yen": 6030000
      },
      "diversity": {
        "scope": null,
        "female_manager_ratio": null,
        "female_to_male_wage_ratio_all": null,
        "female_to_male_wage_ratio_regular": null,
        "female_to_male_wage_ratio_nonregular": null,
        "male_childcare_leave_ratio": null,
        "male_childcare_leave_method": null
      },
      "subsidiaries": [],
      "notes": [
        "多様性指標は有報に記載なし（非公表）。"
      ],
      "is_holding": false,
      "basis_change_note": "",
      "reorganization_note": ""
    },
    {
      "source": {
        "doc_type": "有価証券報告書",
        "doc_id": "S100P22Z",
        "period_end": "2022-05-31",
        "submit_datetime": "2022-08-22 15:45",
        "description": "有価証券報告書－第15期(令和3年6月1日－令和4年5月31日)"
      },
      "employees": {
        "consolidated": 10364,
        "reporting_company": 674,
        "reporting_company_source": "XBRL標準タグと一致",
        "reporting_company_xbrl_standard_tag": 674,
        "consolidated_history": {
          "当期末": 10364,
          "1年前": 9498,
          "2年前": 9657,
          "3年前": 7855,
          "4年前": 7716
        }
      },
      "reporting_company": {
        "average_age_years": 36.8,
        "average_tenure_years": 8.2,
        "average_annual_salary_yen": 6192000
      },
      "diversity": {
        "scope": null,
        "female_manager_ratio": null,
        "female_to_male_wage_ratio_all": null,
        "female_to_male_wage_ratio_regular": null,
        "female_to_male_wage_ratio_nonregular": null,
        "male_childcare_leave_ratio": null,
        "male_childcare_leave_method": null
      },
      "subsidiaries": [],
      "notes": [
        "多様性指標は有報に記載なし（非公表）。"
      ],
      "is_holding": false,
      "basis_change_note": "",
      "reorganization_note": ""
    },
    {
      "source": {
        "doc_type": "有価証券報告書",
        "doc_id": "S100RQYK",
        "period_end": "2023-05-31",
        "submit_datetime": "2023-08-25 13:58",
        "description": "有価証券報告書－第16期(2022/06/01－2023/05/31)"
      },
      "employees": {
        "consolidated": 9786,
        "reporting_company": 731,
        "reporting_company_source": "XBRL標準タグと一致",
        "reporting_company_xbrl_standard_tag": 731,
        "consolidated_history": {
          "当期末": 9786,
          "1年前": 10364,
          "2年前": 9498,
          "3年前": 9657,
          "4年前": 7855
        }
      },
      "reporting_company": {
        "average_age_years": 36.3,
        "average_tenure_years": 7.9,
        "average_annual_salary_yen": 6226000
      },
      "diversity": {
        "scope": null,
        "female_manager_ratio": null,
        "female_to_male_wage_ratio_all": null,
        "female_to_male_wage_ratio_regular": null,
        "female_to_male_wage_ratio_nonregular": null,
        "male_childcare_leave_ratio": null,
        "male_childcare_leave_method": null
      },
      "subsidiaries": [],
      "notes": [
        "多様性指標は有報に記載なし（非公表）。"
      ],
      "is_holding": false,
      "basis_change_note": "",
      "reorganization_note": ""
    },
    {
      "source": {
        "doc_type": "有価証券報告書",
        "doc_id": "S100U9HI",
        "period_end": "2024-05-31",
        "submit_datetime": "2024-08-23 17:04",
        "description": "有価証券報告書－第17期(2023/06/01－2024/05/31)"
      },
      "employees": {
        "consolidated": 10001,
        "reporting_company": 770,
        "reporting_company_source": "XBRL標準タグと一致",
        "reporting_company_xbrl_standard_tag": 770,
        "consolidated_history": {
          "当期末": 10001,
          "1年前": 9786,
          "2年前": 10364,
          "3年前": 9498,
          "4年前": 9657
        }
      },
      "reporting_company": {
        "average_age_years": 36.2,
        "average_tenure_years": 8.1,
        "average_annual_salary_yen": 6276000
      },
      "diversity": {
        "scope": "提出会社",
        "female_manager_ratio": 0.517,
        "female_to_male_wage_ratio_all": 0.891,
        "female_to_male_wage_ratio_regular": 0.88,
        "female_to_male_wage_ratio_nonregular": 0.829,
        "male_childcare_leave_ratio": 0.667,
        "male_childcare_leave_method": "原則方式"
      },
      "subsidiaries": [],
      "notes": [],
      "is_holding": false,
      "basis_change_note": "",
      "reorganization_note": ""
    },
    {
      "source": {
        "doc_type": "有価証券報告書",
        "doc_id": "S100WJZQ",
        "period_end": "2025-05-31",
        "submit_datetime": "2025-08-20 09:00",
        "description": "有価証券報告書－第18期(2024/06/01－2025/05/31)"
      },
      "employees": {
        "consolidated": 8894,
        "reporting_company": 880,
        "reporting_company_source": "XBRL標準タグと一致",
        "reporting_company_xbrl_standard_tag": 880,
        "consolidated_history": {
          "当期末": 8894,
          "1年前": 10001,
          "2年前": 9786,
          "3年前": 10364,
          "4年前": 9498
        }
      },
      "reporting_company": {
        "average_age_years": 34.9,
        "average_tenure_years": 7.7,
        "average_annual_salary_yen": 6289000
      },
      "diversity": {
        "scope": "提出会社",
        "female_manager_ratio": 0.557,
        "female_to_male_wage_ratio_all": 0.856,
        "female_to_male_wage_ratio_regular": 0.848,
        "female_to_male_wage_ratio_nonregular": 0.828,
        "male_childcare_leave_ratio": 0.917,
        "male_childcare_leave_method": "原則方式"
      },
      "subsidiaries": [],
      "notes": [],
      "is_holding": false,
      "basis_change_note": "",
      "reorganization_note": ""
    }
  ],
  "salary_breaks": {},
  "headcount_breaks": {},
  "salary_trend_comparable": true,
  "headcount_trend_comparable": true,
  "trend": {
    "average_annual_salary_yen": {
      "2021-05-31": 6030000,
      "2022-05-31": 6192000,
      "2023-05-31": 6226000,
      "2024-05-31": 6276000,
      "2025-05-31": 6289000
    },
    "employees_reporting_company": {
      "2021-05-31": 645,
      "2022-05-31": 674,
      "2023-05-31": 731,
      "2024-05-31": 770,
      "2025-05-31": 880
    },
    "female_manager_ratio": {
      "2024-05-31": 0.517,
      "2025-05-31": 0.557
    },
    "female_to_male_wage_ratio_all": {
      "2024-05-31": 0.891,
      "2025-05-31": 0.856
    }
  }
}