{
  "edinet_code": "E24753",
  "name": "株式会社トランザクション",
  "sec_code": "78180",
  "industry": "その他製品",
  "peer_group": "その他製品",
  "is_holding": false,
  "latest": {
    "source": {
      "doc_type": "有価証券報告書",
      "doc_id": "S100X6MS",
      "period_end": "2025-08-31",
      "submit_datetime": "2025-11-26 13:32",
      "description": "有価証券報告書－第39期(2024/09/01－2025/08/31)"
    },
    "employees": {
      "consolidated": 495,
      "reporting_company": 30,
      "reporting_company_source": "XBRL標準タグと一致",
      "reporting_company_xbrl_standard_tag": 30,
      "consolidated_history": {
        "当期末": 495,
        "1年前": 481,
        "2年前": 455,
        "3年前": 442,
        "4年前": 453
      }
    },
    "reporting_company": {
      "average_age_years": 40.4,
      "average_tenure_years": 6.4,
      "average_annual_salary_yen": 5909000
    },
    "diversity": {
      "scope": "提出会社",
      "female_manager_ratio": 0.313,
      "female_to_male_wage_ratio_all": 0.649,
      "female_to_male_wage_ratio_regular": 0.672,
      "female_to_male_wage_ratio_nonregular": 0.251,
      "male_childcare_leave_ratio": null,
      "male_childcare_leave_method": "原則方式"
    },
    "subsidiaries": [],
    "notes": [],
    "is_holding": false,
    "basis_change_note": "",
    "reorganization_note": ""
  },
  "years": [
    {
      "source": {
        "doc_type": "有価証券報告書",
        "doc_id": "S100MXV2",
        "period_end": "2021-08-31",
        "submit_datetime": "2021-11-26 15:03",
        "description": "有価証券報告書－第35期(令和2年9月1日－令和3年8月31日)"
      },
      "employees": {
        "consolidated": 453,
        "reporting_company": 27,
        "reporting_company_source": "XBRL標準タグと一致",
        "reporting_company_xbrl_standard_tag": 27,
        "consolidated_history": {
          "当期末": 453,
          "1年前": 476,
          "2年前": 442,
          "3年前": 456,
          "4年前": 415
        }
      },
      "reporting_company": {
        "average_age_years": 38.5,
        "average_tenure_years": 6.3,
        "average_annual_salary_yen": 5554000
      },
      "diversity": {
        "scope": null,
        "female_manager_ratio": null,
        "female_to_male_wage_ratio_all": null,
        "female_to_male_wage_ratio_regular": null,
        "female_to_male_wage_ratio_nonregular": null,
        "male_childcare_leave_ratio": null,
        "male_childcare_leave_method": null
      },
      "subsidiaries": [],
      "notes": [
        "多様性指標は有報に記載なし（非公表）。"
      ],
      "is_holding": false,
      "basis_change_note": "",
      "reorganization_note": ""
    },
    {
      "source": {
        "doc_type": "有価証券報告書",
        "doc_id": "S100PP1Z",
        "period_end": "2022-08-31",
        "submit_datetime": "2022-11-29 15:05",
        "description": "有価証券報告書－第36期(令和3年9月1日－令和4年8月31日)"
      },
      "employees": {
        "consolidated": 442,
        "reporting_company": 27,
        "reporting_company_source": "XBRL標準タグと一致",
        "reporting_company_xbrl_standard_tag": 27,
        "consolidated_history": {
          "当期末": 442,
          "1年前": 453,
          "2年前": 476,
          "3年前": 442,
          "4年前": 456
        }
      },
      "reporting_company": {
        "average_age_years": 39.9,
        "average_tenure_years": 5.4,
        "average_annual_salary_yen": 5543000
      },
      "diversity": {
        "scope": null,
        "female_manager_ratio": null,
        "female_to_male_wage_ratio_all": null,
        "female_to_male_wage_ratio_regular": null,
        "female_to_male_wage_ratio_nonregular": null,
        "male_childcare_leave_ratio": null,
        "male_childcare_leave_method": null
      },
      "subsidiaries": [],
      "notes": [
        "多様性指標は有報に記載なし（非公表）。"
      ],
      "is_holding": false,
      "basis_change_note": "",
      "reorganization_note": ""
    },
    {
      "source": {
        "doc_type": "有価証券報告書",
        "doc_id": "S100SD2N",
        "period_end": "2023-08-31",
        "submit_datetime": "2023-11-29 15:25",
        "description": "有価証券報告書－第37期(2022/09/01－2023/08/31)"
      },
      "employees": {
        "consolidated": 455,
        "reporting_company": 28,
        "reporting_company_source": "XBRL標準タグと一致",
        "reporting_company_xbrl_standard_tag": 28,
        "consolidated_history": {
          "当期末": 455,
          "1年前": 442,
          "2年前": 453,
          "3年前": 476,
          "4年前": 442
        }
      },
      "reporting_company": {
        "average_age_years": 38.3,
        "average_tenure_years": 4.9,
        "average_annual_salary_yen": 5575000
      },
      "diversity": {
        "scope": null,
        "female_manager_ratio": null,
        "female_to_male_wage_ratio_all": null,
        "female_to_male_wage_ratio_regular": null,
        "female_to_male_wage_ratio_nonregular": null,
        "male_childcare_leave_ratio": null,
        "male_childcare_leave_method": null
      },
      "subsidiaries": [],
      "notes": [
        "多様性指標は有報に記載なし（非公表）。"
      ],
      "is_holding": false,
      "basis_change_note": "",
      "reorganization_note": ""
    },
    {
      "source": {
        "doc_type": "有価証券報告書",
        "doc_id": "S100UUQV",
        "period_end": "2024-08-31",
        "submit_datetime": "2024-11-28 13:17",
        "description": "有価証券報告書－第38期(2023/09/01－2024/08/31)"
      },
      "employees": {
        "consolidated": 481,
        "reporting_company": 32,
        "reporting_company_source": "XBRL標準タグと一致",
        "reporting_company_xbrl_standard_tag": 32,
        "consolidated_history": {
          "当期末": 481,
          "1年前": 455,
          "2年前": 442,
          "3年前": 453,
          "4年前": 476
        }
      },
      "reporting_company": {
        "average_age_years": 39.3,
        "average_tenure_years": 5.1,
        "average_annual_salary_yen": 5728000
      },
      "diversity": {
        "scope": "提出会社",
        "female_manager_ratio": 0.294,
        "female_to_male_wage_ratio_all": 0.654,
        "female_to_male_wage_ratio_regular": 0.664,
        "female_to_male_wage_ratio_nonregular": 0.196,
        "male_childcare_leave_ratio": null,
        "male_childcare_leave_method": "原則方式"
      },
      "subsidiaries": [],
      "notes": [],
      "is_holding": false,
      "basis_change_note": "",
      "reorganization_note": ""
    },
    {
      "source": {
        "doc_type": "有価証券報告書",
        "doc_id": "S100X6MS",
        "period_end": "2025-08-31",
        "submit_datetime": "2025-11-26 13:32",
        "description": "有価証券報告書－第39期(2024/09/01－2025/08/31)"
      },
      "employees": {
        "consolidated": 495,
        "reporting_company": 30,
        "reporting_company_source": "XBRL標準タグと一致",
        "reporting_company_xbrl_standard_tag": 30,
        "consolidated_history": {
          "当期末": 495,
          "1年前": 481,
          "2年前": 455,
          "3年前": 442,
          "4年前": 453
        }
      },
      "reporting_company": {
        "average_age_years": 40.4,
        "average_tenure_years": 6.4,
        "average_annual_salary_yen": 5909000
      },
      "diversity": {
        "scope": "提出会社",
        "female_manager_ratio": 0.313,
        "female_to_male_wage_ratio_all": 0.649,
        "female_to_male_wage_ratio_regular": 0.672,
        "female_to_male_wage_ratio_nonregular": 0.251,
        "male_childcare_leave_ratio": null,
        "male_childcare_leave_method": "原則方式"
      },
      "subsidiaries": [],
      "notes": [],
      "is_holding": false,
      "basis_change_note": "",
      "reorganization_note": ""
    }
  ],
  "salary_breaks": {},
  "headcount_breaks": {},
  "salary_trend_comparable": true,
  "headcount_trend_comparable": true,
  "trend": {
    "average_annual_salary_yen": {
      "2021-08-31": 5554000,
      "2022-08-31": 5543000,
      "2023-08-31": 5575000,
      "2024-08-31": 5728000,
      "2025-08-31": 5909000
    },
    "employees_reporting_company": {
      "2021-08-31": 27,
      "2022-08-31": 27,
      "2023-08-31": 28,
      "2024-08-31": 32,
      "2025-08-31": 30
    },
    "female_manager_ratio": {
      "2024-08-31": 0.294,
      "2025-08-31": 0.313
    },
    "female_to_male_wage_ratio_all": {
      "2024-08-31": 0.654,
      "2025-08-31": 0.649
    }
  }
}